cktool/__init__.py
cktool/cktool.py
cktool/formation.svg
cktool-0.0.1.dist-info/LICENSE
cktool-0.0.1.dist-info/METADATA
cktool-0.0.1.dist-info/WHEEL
cktool-0.0.1.dist-info/entry_points.txt
cktool-0.0.1.dist-info/top_level.txt
cktool-0.0.1.dist-info/RECORD
