Metadata-Version: 2.1
Name: cktool
Version: 0.0.1
Summary: Command line tool for dealing with clubkatsudo.com chores
Home-page: https://github.com/ammgws/cktool
License: UNKNOWN
Keywords: clubkatsudo clubkatsudo.com
Platform: UNKNOWN
Classifier: Programming Language :: Python :: 3
Classifier: License :: OSI Approved :: MIT License
Classifier: Operating System :: OS Independent
Requires-Python: >=3.7
Requires-Dist: click
Requires-Dist: reportlab
Requires-Dist: requests
Requires-Dist: requests-html
Requires-Dist: svglib
Requires-Dist: toml
